<?xml version="1.0" encoding="UTF-8" standalone="no"?>
<Index>
<Entry>
<Term>algorithm</Term>
<Count>1</Count>
</Entry>
<Entry>
<Term>ca630926</Term>
<Count>1</Count>
</Entry>
<Entry>
<Term>cacm</Term>
<Count>1</Count>
</Entry>
<Entry>
<Term>carlo</Term>
<Count>1</Count>
</Entry>
<Entry>
<Term>d</Term>
<Count>1</Count>
</Entry>
<Entry>
<Term>inverse</Term>
<Count>1</Count>
</Entry>
<Entry>
<Term>jb</Term>
<Count>1</Count>
</Entry>
<Entry>
<Term>march</Term>
<Count>1</Count>
</Entry>
<Entry>
<Term>monte</Term>
<Count>1</Count>
</Entry>
<Entry>
<Term>pm</Term>
<Count>1</Count>
</Entry>
<Entry>
<Term>rodmanr</Term>
<Count>1</Count>
</Entry>
<Entry>
<Term>september</Term>
<Count>1</Count>
</Entry>
</Index>
