<?xml version="1.0" encoding="UTF-8" standalone="no"?>
<Index>
<Entry>
<Term>a</Term>
<Count>1</Count>
</Entry>
<Entry>
<Term>am</Term>
<Count>1</Count>
</Entry>
<Entry>
<Term>arithmetic</Term>
<Count>1</Count>
</Entry>
<Entry>
<Term>august</Term>
<Count>1</Count>
</Entry>
<Entry>
<Term>ca740807</Term>
<Count>1</Count>
</Entry>
<Entry>
<Term>cacm</Term>
<Count>1</Count>
</Entry>
<Entry>
<Term>denning</Term>
<Count>1</Count>
</Entry>
<Entry>
<Term>evaluation</Term>
<Count>1</Count>
</Entry>
<Entry>
<Term>expressions</Term>
<Count>1</Count>
</Entry>
<Entry>
<Term>g</Term>
<Count>1</Count>
</Entry>
<Entry>
<Term>graham</Term>
<Count>1</Count>
</Entry>
<Entry>
<Term>in</Term>
<Count>1</Count>
</Entry>
<Entry>
<Term>j</Term>
<Count>1</Count>
</Entry>
<Entry>
<Term>january</Term>
<Count>1</Count>
</Entry>
<Entry>
<Term>jb</Term>
<Count>1</Count>
</Entry>
<Entry>
<Term>note</Term>
<Count>1</Count>
</Entry>
<Entry>
<Term>of</Term>
<Count>1</Count>
</Entry>
<Entry>
<Term>on</Term>
<Count>1</Count>
</Entry>
<Entry>
<Term>ordering</Term>
<Count>1</Count>
</Entry>
<Entry>
<Term>p</Term>
<Count>1</Count>
</Entry>
<Entry>
<Term>s</Term>
<Count>1</Count>
</Entry>
<Entry>
<Term>subexpression</Term>
<Count>1</Count>
</Entry>
<Entry>
<Term>the</Term>
<Count>1</Count>
</Entry>
</Index>
