<?xml version="1.0" encoding="UTF-8" standalone="no"?>
<Index>
<Entry>
<Term>algorithms</Term>
<Count>1</Count>
</Entry>
<Entry>
<Term>ca690904</Term>
<Count>1</Count>
</Entry>
<Entry>
<Term>cacm</Term>
<Count>1</Count>
</Entry>
<Entry>
<Term>d</Term>
<Count>1</Count>
</Entry>
<Entry>
<Term>february</Term>
<Count>1</Count>
</Entry>
<Entry>
<Term>generator</Term>
<Count>1</Count>
</Entry>
<Entry>
<Term>graphs</Term>
<Count>1</Count>
</Entry>
<Entry>
<Term>h</Term>
<Count>1</Count>
</Entry>
<Entry>
<Term>jb</Term>
<Count>1</Count>
</Entry>
<Entry>
<Term>m</Term>
<Count>1</Count>
</Entry>
<Entry>
<Term>mcilroy</Term>
<Count>1</Count>
</Entry>
<Entry>
<Term>of</Term>
<Count>1</Count>
</Entry>
<Entry>
<Term>pm</Term>
<Count>1</Count>
</Entry>
<Entry>
<Term>september</Term>
<Count>1</Count>
</Entry>
<Entry>
<Term>spanning</Term>
<Count>2</Count>
</Entry>
<Entry>
<Term>trees</Term>
<Count>3</Count>
</Entry>
</Index>
