<?xml version="1.0" encoding="UTF-8" standalone="no"?>
<Index>
<Entry>
<Term>a</Term>
<Count>4</Count>
</Entry>
<Entry>
<Term>algorithm</Term>
<Count>2</Count>
</Entry>
<Entry>
<Term>ambit</Term>
<Count>5</Count>
</Entry>
<Entry>
<Term>an</Term>
<Count>1</Count>
</Entry>
<Entry>
<Term>and</Term>
<Count>2</Count>
</Entry>
<Entry>
<Term>applicable</Term>
<Count>1</Count>
</Entry>
<Entry>
<Term>application</Term>
<Count>1</Count>
</Entry>
<Entry>
<Term>are</Term>
<Count>1</Count>
</Entry>
<Entry>
<Term>august</Term>
<Count>1</Count>
</Entry>
<Entry>
<Term>brief</Term>
<Count>1</Count>
</Entry>
<Entry>
<Term>c</Term>
<Count>1</Count>
</Entry>
<Entry>
<Term>ca660803</Term>
<Count>1</Count>
</Entry>
<Entry>
<Term>cacm</Term>
<Count>1</Count>
</Entry>
<Entry>
<Term>christensen</Term>
<Count>1</Count>
</Entry>
<Entry>
<Term>description</Term>
<Count>1</Count>
</Entry>
<Entry>
<Term>design</Term>
<Count>1</Count>
</Entry>
<Entry>
<Term>example</Term>
<Count>1</Count>
</Entry>
<Entry>
<Term>family</Term>
<Count>1</Count>
</Entry>
<Entry>
<Term>for</Term>
<Count>4</Count>
</Entry>
<Entry>
<Term>given</Term>
<Count>2</Count>
</Entry>
<Entry>
<Term>implementation</Term>
<Count>2</Count>
</Entry>
<Entry>
<Term>is</Term>
<Count>3</Count>
</Entry>
<Entry>
<Term>it</Term>
<Count>1</Count>
</Entry>
<Entry>
<Term>its</Term>
<Count>1</Count>
</Entry>
<Entry>
<Term>jb</Term>
<Count>1</Count>
</Entry>
<Entry>
<Term>language</Term>
<Count>3</Count>
</Entry>
<Entry>
<Term>languages</Term>
<Count>1</Count>
</Entry>
<Entry>
<Term>manipulation</Term>
<Count>1</Count>
</Entry>
<Entry>
<Term>march</Term>
<Count>1</Count>
</Entry>
<Entry>
<Term>member</Term>
<Count>1</Count>
</Entry>
<Entry>
<Term>members</Term>
<Count>1</Count>
</Entry>
<Entry>
<Term>of</Term>
<Count>8</Count>
</Entry>
<Entry>
<Term>on</Term>
<Count>1</Count>
</Entry>
<Entry>
<Term>other</Term>
<Count>1</Count>
</Entry>
<Entry>
<Term>pm</Term>
<Count>1</Count>
</Entry>
<Entry>
<Term>programming</Term>
<Count>1</Count>
</Entry>
<Entry>
<Term>provides</Term>
<Count>1</Count>
</Entry>
<Entry>
<Term>rationale</Term>
<Count>1</Count>
</Entry>
<Entry>
<Term>replacement</Term>
<Count>1</Count>
</Entry>
<Entry>
<Term>rule</Term>
<Count>1</Count>
</Entry>
<Entry>
<Term>scan</Term>
<Count>1</Count>
</Entry>
<Entry>
<Term>string</Term>
<Count>1</Count>
</Entry>
<Entry>
<Term>symbol</Term>
<Count>1</Count>
</Entry>
<Entry>
<Term>technique</Term>
<Count>1</Count>
</Entry>
<Entry>
<Term>the</Term>
<Count>10</Count>
</Entry>
<Entry>
<Term>to</Term>
<Count>1</Count>
</Entry>
<Entry>
<Term>transformation</Term>
<Count>1</Count>
</Entry>
<Entry>
<Term>which</Term>
<Count>1</Count>
</Entry>
</Index>
