<?xml version="1.0" encoding="UTF-8" standalone="no"?>
<Index>
<Entry>
<Term>a</Term>
<Count>7</Count>
</Entry>
<Entry>
<Term>accept</Term>
<Count>2</Count>
</Entry>
<Entry>
<Term>adamd</Term>
<Count>1</Count>
</Entry>
<Entry>
<Term>adequapproxim</Term>
<Count>1</Count>
</Entry>
<Entry>
<Term>algorithm</Term>
<Count>1</Count>
</Entry>
<Entry>
<Term>allow</Term>
<Count>1</Count>
</Entry>
<Entry>
<Term>an</Term>
<Count>2</Count>
</Entry>
<Entry>
<Term>and</Term>
<Count>1</Count>
</Entry>
<Entry>
<Term>as</Term>
<Count>1</Count>
</Entry>
<Entry>
<Term>asa</Term>
<Count>1</Count>
</Entry>
<Entry>
<Term>basi</Term>
<Count>1</Count>
</Entry>
<Entry>
<Term>been</Term>
<Count>1</Count>
</Entry>
<Entry>
<Term>beentest</Term>
<Count>1</Count>
</Entry>
<Entry>
<Term>bound</Term>
<Count>1</Count>
</Entry>
<Entry>
<Term>ca671009</Term>
<Count>1</Count>
</Entry>
<Entry>
<Term>cacm</Term>
<Count>1</Count>
</Entry>
<Entry>
<Term>calcul</Term>
<Count>1</Count>
</Entry>
<Entry>
<Term>complex</Term>
<Count>1</Count>
</Entry>
<Entry>
<Term>criterion</Term>
<Count>2</Count>
</Entry>
<Entry>
<Term>difficult</Term>
<Count>1</Count>
</Entry>
<Entry>
<Term>error</Term>
<Count>1</Count>
</Entry>
<Entry>
<Term>evalu</Term>
<Count>1</Count>
</Entry>
<Entry>
<Term>exampl</Term>
<Count>1</Count>
</Entry>
<Entry>
<Term>februari</Term>
<Count>1</Count>
</Entry>
<Entry>
<Term>find</Term>
<Count>1</Count>
</Entry>
<Entry>
<Term>for</Term>
<Count>3</Count>
</Entry>
<Entry>
<Term>forthe</Term>
<Count>1</Count>
</Entry>
<Entry>
<Term>found</Term>
<Count>1</Count>
</Entry>
<Entry>
<Term>gener</Term>
<Count>1</Count>
</Entry>
<Entry>
<Term>ha</Term>
<Count>2</Count>
</Entry>
<Entry>
<Term>in</Term>
<Count>2</Count>
</Entry>
<Entry>
<Term>is</Term>
<Count>1</Count>
</Entry>
<Entry>
<Term>ispresent</Term>
<Count>1</Count>
</Entry>
<Entry>
<Term>it</Term>
<Count>1</Count>
</Entry>
<Entry>
<Term>iter</Term>
<Count>1</Count>
</Entry>
<Entry>
<Term>jb</Term>
<Count>1</Count>
</Entry>
<Entry>
<Term>just</Term>
<Count>1</Count>
</Entry>
<Entry>
<Term>mean</Term>
<Count>1</Count>
</Entry>
<Entry>
<Term>number</Term>
<Count>2</Count>
</Entry>
<Entry>
<Term>numer</Term>
<Count>1</Count>
</Entry>
<Entry>
<Term>octob</Term>
<Count>1</Count>
</Entry>
<Entry>
<Term>of</Term>
<Count>3</Count>
</Entry>
<Entry>
<Term>on</Term>
<Count>2</Count>
</Entry>
<Entry>
<Term>onthe</Term>
<Count>1</Count>
</Entry>
<Entry>
<Term>paper</Term>
<Count>1</Count>
</Entry>
<Entry>
<Term>pm1524</Term>
<Count>1</Count>
</Entry>
<Entry>
<Term>polynomi</Term>
<Count>4</Count>
</Entry>
<Entry>
<Term>process</Term>
<Count>1</Count>
</Entry>
<Entry>
<Term>real</Term>
<Count>1</Count>
</Entry>
<Entry>
<Term>root</Term>
<Count>3</Count>
</Entry>
<Entry>
<Term>roundoff</Term>
<Count>1</Count>
</Entry>
<Entry>
<Term>satisfactori</Term>
<Count>1</Count>
</Entry>
<Entry>
<Term>search</Term>
<Count>1</Count>
</Entry>
<Entry>
<Term>servas</Term>
<Count>1</Count>
</Entry>
<Entry>
<Term>stop</Term>
<Count>2</Count>
</Entry>
<Entry>
<Term>termin</Term>
<Count>1</Count>
</Entry>
<Entry>
<Term>the</Term>
<Count>4</Count>
</Entry>
<Entry>
<Term>thi</Term>
<Count>2</Count>
</Entry>
<Entry>
<Term>to</Term>
<Count>4</Count>
</Entry>
<Entry>
<Term>toknow</Term>
<Count>1</Count>
</Entry>
<Entry>
<Term>when</Term>
<Count>2</Count>
</Entry>
<Entry>
<Term>which</Term>
<Count>1</Count>
</Entry>
<Entry>
<Term>whichoccur</Term>
<Count>1</Count>
</Entry>
<Entry>
<Term>zero</Term>
<Count>1</Count>
</Entry>
</Index>
