<?xml version="1.0" encoding="UTF-8" standalone="no"?>
<Index>
<Entry>
<Term>a</Term>
<Count>2</Count>
</Entry>
<Entry>
<Term>adebug</Term>
<Count>1</Count>
</Entry>
<Entry>
<Term>aid</Term>
<Count>1</Count>
</Entry>
<Entry>
<Term>associ</Term>
<Count>1</Count>
</Entry>
<Entry>
<Term>at</Term>
<Count>1</Count>
</Entry>
<Entry>
<Term>by</Term>
<Count>1</Count>
</Entry>
<Entry>
<Term>ca640704</Term>
<Count>1</Count>
</Entry>
<Entry>
<Term>cacm</Term>
<Count>1</Count>
</Entry>
<Entry>
<Term>complex</Term>
<Count>1</Count>
</Entry>
<Entry>
<Term>data</Term>
<Count>4</Count>
</Entry>
<Entry>
<Term>debug</Term>
<Count>2</Count>
</Entry>
<Entry>
<Term>desir</Term>
<Count>1</Count>
</Entry>
<Entry>
<Term>extract</Term>
<Count>3</Count>
</Entry>
<Entry>
<Term>high</Term>
<Count>2</Count>
</Entry>
<Entry>
<Term>identif</Term>
<Count>1</Count>
</Entry>
<Entry>
<Term>in</Term>
<Count>1</Count>
</Entry>
<Entry>
<Term>interrupt</Term>
<Count>1</Count>
</Entry>
<Entry>
<Term>is</Term>
<Count>2</Count>
</Entry>
<Entry>
<Term>it</Term>
<Count>1</Count>
</Entry>
<Entry>
<Term>jbmarch</Term>
<Count>1</Count>
</Entry>
<Entry>
<Term>juli</Term>
<Count>1</Count>
</Entry>
<Entry>
<Term>l</Term>
<Count>1</Count>
</Entry>
<Entry>
<Term>languag</Term>
<Count>1</Count>
</Entry>
<Entry>
<Term>lateredit</Term>
<Count>1</Count>
</Entry>
<Entry>
<Term>level</Term>
<Count>2</Count>
</Entry>
<Entry>
<Term>list</Term>
<Count>1</Count>
</Entry>
<Entry>
<Term>look</Term>
<Count>1</Count>
</Entry>
<Entry>
<Term>mean</Term>
<Count>1</Count>
</Entry>
<Entry>
<Term>pm</Term>
<Count>1</Count>
</Entry>
<Entry>
<Term>pointto</Term>
<Count>1</Count>
</Entry>
<Entry>
<Term>previous</Term>
<Count>1</Count>
</Entry>
<Entry>
<Term>program</Term>
<Count>1</Count>
</Entry>
<Entry>
<Term>r</Term>
<Count>1</Count>
</Entry>
<Entry>
<Term>real</Term>
<Count>1</Count>
</Entry>
<Entry>
<Term>realtime</Term>
<Count>1</Count>
</Entry>
<Entry>
<Term>sourc</Term>
<Count>1</Count>
</Entry>
<Entry>
<Term>sourclanguag</Term>
<Count>1</Count>
</Entry>
<Entry>
<Term>specifi</Term>
<Count>1</Count>
</Entry>
<Entry>
<Term>substanti</Term>
<Count>1</Count>
</Entry>
<Entry>
<Term>system</Term>
<Count>1</Count>
</Entry>
<Entry>
<Term>take</Term>
<Count>1</Count>
</Entry>
<Entry>
<Term>talk</Term>
<Count>2</Count>
</Entry>
<Entry>
<Term>techniqu</Term>
<Count>2</Count>
</Entry>
<Entry>
<Term>the</Term>
<Count>3</Count>
</Entry>
<Entry>
<Term>timeprogram</Term>
<Count>1</Count>
</Entry>
<Entry>
<Term>user</Term>
<Count>1</Count>
</Entry>
<Entry>
<Term>versteeg</Term>
<Count>1</Count>
</Entry>
<Entry>
<Term>which</Term>
<Count>1</Count>
</Entry>
<Entry>
<Term>with</Term>
<Count>2</Count>
</Entry>
</Index>
