<?xml version="1.0" encoding="UTF-8" standalone="no"?>
<Index>
<Entry>
<Term>a</Term>
<Count>3</Count>
</Entry>
<Entry>
<Term>altern</Term>
<Count>1</Count>
</Entry>
<Entry>
<Term>an</Term>
<Count>2</Count>
</Entry>
<Entry>
<Term>anequival</Term>
<Count>1</Count>
</Entry>
<Entry>
<Term>applic</Term>
<Count>1</Count>
</Entry>
<Entry>
<Term>ar</Term>
<Count>2</Count>
</Entry>
<Entry>
<Term>as</Term>
<Count>1</Count>
</Entry>
<Entry>
<Term>baker</Term>
<Count>1</Count>
</Entry>
<Entry>
<Term>be</Term>
<Count>1</Count>
</Entry>
<Entry>
<Term>binari</Term>
<Count>2</Count>
</Entry>
<Entry>
<Term>ca650512</Term>
<Count>1</Count>
</Entry>
<Entry>
<Term>cacm</Term>
<Count>1</Count>
</Entry>
<Entry>
<Term>chang</Term>
<Count>1</Count>
</Entry>
<Entry>
<Term>characterist</Term>
<Count>1</Count>
</Entry>
<Entry>
<Term>comput</Term>
<Count>1</Count>
</Entry>
<Entry>
<Term>decim</Term>
<Count>1</Count>
</Entry>
<Entry>
<Term>differ</Term>
<Count>1</Count>
</Entry>
<Entry>
<Term>each</Term>
<Count>1</Count>
</Entry>
<Entry>
<Term>easili</Term>
<Count>1</Count>
</Entry>
<Entry>
<Term>either</Term>
<Count>1</Count>
</Entry>
<Entry>
<Term>equival</Term>
<Count>1</Count>
</Entry>
<Entry>
<Term>exampl</Term>
<Count>1</Count>
</Entry>
<Entry>
<Term>express</Term>
<Count>3</Count>
</Entry>
<Entry>
<Term>expressfor</Term>
<Count>1</Count>
</Entry>
<Entry>
<Term>form</Term>
<Count>2</Count>
</Entry>
<Entry>
<Term>four</Term>
<Count>1</Count>
</Entry>
<Entry>
<Term>gain</Term>
<Count>1</Count>
</Entry>
<Entry>
<Term>given</Term>
<Count>1</Count>
</Entry>
<Entry>
<Term>have</Term>
<Count>1</Count>
</Entry>
<Entry>
<Term>in</Term>
<Count>1</Count>
</Entry>
<Entry>
<Term>inwhich</Term>
<Count>1</Count>
</Entry>
<Entry>
<Term>is</Term>
<Count>1</Count>
</Entry>
<Entry>
<Term>j</Term>
<Count>1</Count>
</Entry>
<Entry>
<Term>jb</Term>
<Count>1</Count>
</Entry>
<Entry>
<Term>l</Term>
<Count>1</Count>
</Entry>
<Entry>
<Term>letter</Term>
<Count>1</Count>
</Entry>
<Entry>
<Term>mai1965</Term>
<Count>1</Count>
</Entry>
<Entry>
<Term>march7</Term>
<Count>1</Count>
</Entry>
<Entry>
<Term>number</Term>
<Count>1</Count>
</Entry>
<Entry>
<Term>numbercan</Term>
<Count>1</Count>
</Entry>
<Entry>
<Term>numberthere</Term>
<Count>1</Count>
</Entry>
<Entry>
<Term>of</Term>
<Count>5</Count>
</Entry>
<Entry>
<Term>onanoth</Term>
<Count>1</Count>
</Entry>
<Entry>
<Term>or</Term>
<Count>2</Count>
</Entry>
<Entry>
<Term>pm</Term>
<Count>1</Count>
</Entry>
<Entry>
<Term>power</Term>
<Count>1</Count>
</Entry>
<Entry>
<Term>r</Term>
<Count>2</Count>
</Entry>
<Entry>
<Term>routin</Term>
<Count>1</Count>
</Entry>
<Entry>
<Term>save</Term>
<Count>1</Count>
</Entry>
<Entry>
<Term>set</Term>
<Count>1</Count>
</Entry>
<Entry>
<Term>space</Term>
<Count>1</Count>
</Entry>
<Entry>
<Term>the</Term>
<Count>1</Count>
</Entry>
<Entry>
<Term>then</Term>
<Count>1</Count>
</Entry>
<Entry>
<Term>thought</Term>
<Count>1</Count>
</Entry>
<Entry>
<Term>three</Term>
<Count>1</Count>
</Entry>
<Entry>
<Term>to</Term>
<Count>3</Count>
</Entry>
<Entry>
<Term>translat</Term>
<Count>1</Count>
</Entry>
<Entry>
<Term>weldon</Term>
<Count>1</Count>
</Entry>
</Index>
