<?xml version="1.0" encoding="UTF-8" standalone="no"?><Index><Entry><Term>04</Term><Count>1</Count></Entry><Entry><Term>1972</Term><Count>1</Count></Entry><Entry><Term>1978</Term><Count>1</Count></Entry><Entry><Term>2240</Term><Count>6</Count></Entry><Entry><Term>27</Term><Count>1</Count></Entry><Entry><Term>5</Term><Count>3</Count></Entry><Entry><Term>55</Term><Count>1</Count></Entry><Entry><Term>9</Term><Count>1</Count></Entry><Entry><Term>AM</Term><Count>1</Count></Entry><Entry><Term>Algorithm</Term><Count>1</Count></Entry><Entry><Term>C266</Term><Count>1</Count></Entry><Entry><Term>CA721215</Term><Count>1</Count></Entry><Entry><Term>CACM</Term><Count>1</Count></Entry><Entry><Term>December</Term><Count>1</Count></Entry><Entry><Term>G5</Term><Count>1</Count></Entry><Entry><Term>JB</Term><Count>1</Count></Entry><Entry><Term>January</Term><Count>1</Count></Entry><Entry><Term>L</Term><Count>1</Count></Entry><Entry><Term>Numbers</Term><Count>1</Count></Entry><Entry><Term>Pseudo</Term><Count>1</Count></Entry><Entry><Term>Random</Term><Count>1</Count></Entry><Entry><Term>Sullins</Term><Count>1</Count></Entry><Entry><Term>W</Term><Count>1</Count></Entry><Entry><Term>generators</Term><Count>1</Count></Entry><Entry><Term>number</Term><Count>1</Count></Entry><Entry><Term>numbers</Term><Count>1</Count></Entry><Entry><Term>pseudo</Term><Count>1</Count></Entry><Entry><Term>random</Term><Count>2</Count></Entry><Entry><Term>testing</Term><Count>1</Count></Entry></Index>