<?xml version="1.0" encoding="UTF-8" standalone="no"?><Index><Entry><Term>1704</Term><Count>6</Count></Entry><Entry><Term>1968</Term><Count>1</Count></Entry><Entry><Term>1978</Term><Count>1</Count></Entry><Entry><Term>217</Term><Count>1</Count></Entry><Entry><Term>22</Term><Count>1</Count></Entry><Entry><Term>359</Term><Count>1</Count></Entry><Entry><Term>5</Term><Count>3</Count></Entry><Entry><Term>52</Term><Count>1</Count></Entry><Entry><Term>541</Term><Count>1</Count></Entry><Entry><Term>9</Term><Count>1</Count></Entry><Entry><Term>ALgorithm</Term><Count>1</Count></Entry><Entry><Term>AM</Term><Count>1</Count></Entry><Entry><Term>August</Term><Count>1</Count></Entry><Entry><Term>CA680810</Term><Count>1</Count></Entry><Entry><Term>CACM</Term><Count>1</Count></Entry><Entry><Term>Cost</Term><Count>1</Count></Entry><Entry><Term>Curve</Term><Count>1</Count></Entry><Entry><Term>Excess</Term><Count>1</Count></Entry><Entry><Term>F</Term><Count>1</Count></Entry><Entry><Term>February</Term><Count>1</Count></Entry><Entry><Term>H</Term><Count>1</Count></Entry><Entry><Term>J</Term><Count>1</Count></Entry><Entry><Term>JB</Term><Count>1</Count></Entry><Entry><Term>Minimum</Term><Count>1</Count></Entry><Entry><Term>Muth</Term><Count>1</Count></Entry><Entry><Term>PERT</Term><Count>1</Count></Entry><Entry><Term>costtime</Term><Count>1</Count></Entry><Entry><Term>critical</Term><Count>1</Count></Entry><Entry><Term>flows</Term><Count>1</Count></Entry><Entry><Term>network</Term><Count>1</Count></Entry><Entry><Term>path</Term><Count>1</Count></Entry><Entry><Term>scheduling</Term><Count>1</Count></Entry><Entry><Term>tradeoffs</Term><Count>1</Count></Entry></Index>