<?xml version="1.0" encoding="UTF-8" standalone="no"?>
<Index>
<Entry>
<Term>1340</Term>
<Count>6</Count>
</Entry>
<Entry>
<Term>1966</Term>
<Count>1</Count>
</Entry>
<Entry>
<Term>1978</Term>
<Count>1</Count>
</Entry>
<Entry>
<Term>2</Term>
<Count>2</Count>
</Entry>
<Entry>
<Term>25</Term>
<Count>1</Count>
</Entry>
<Entry>
<Term>5</Term>
<Count>3</Count>
</Entry>
<Entry>
<Term>a</Term>
<Count>1</Count>
</Entry>
<Entry>
<Term>abraham</Term>
<Count>1</Count>
</Entry>
<Entry>
<Term>allows</Term>
<Count>1</Count>
</Entry>
<Entry>
<Term>be</Term>
<Count>1</Count>
</Entry>
<Entry>
<Term>c</Term>
<Count>1</Count>
</Entry>
<Entry>
<Term>ca661209</Term>
<Count>1</Count>
</Entry>
<Entry>
<Term>cacm</Term>
<Count>1</Count>
</Entry>
<Entry>
<Term>december</Term>
<Count>1</Count>
</Entry>
<Entry>
<Term>devices</Term>
<Count>1</Count>
</Entry>
<Entry>
<Term>g</Term>
<Count>1</Count>
</Entry>
<Entry>
<Term>is</Term>
<Count>1</Count>
</Entry>
<Entry>
<Term>jb</Term>
<Count>1</Count>
</Entry>
<Entry>
<Term>lance</Term>
<Count>1</Count>
</Entry>
<Entry>
<Term>march</Term>
<Count>1</Count>
</Entry>
<Entry>
<Term>monitor</Term>
<Count>1</Count>
</Entry>
<Entry>
<Term>multiplexed</Term>
<Count>1</Count>
</Entry>
<Entry>
<Term>multiplexing</Term>
<Count>1</Count>
</Entry>
<Entry>
<Term>n</Term>
<Count>1</Count>
</Entry>
<Entry>
<Term>of</Term>
<Count>2</Count>
</Entry>
<Entry>
<Term>output</Term>
<Count>1</Count>
</Entry>
<Entry>
<Term>pearcey</Term>
<Count>1</Count>
</Entry>
<Entry>
<Term>peripherals</Term>
<Count>1</Count>
</Entry>
<Entry>
<Term>philosophy</Term>
<Count>1</Count>
</Entry>
<Entry>
<Term>pm</Term>
<Count>1</Count>
</Entry>
<Entry>
<Term>presented</Term>
<Count>1</Count>
</Entry>
<Entry>
<Term>slow</Term>
<Count>2</Count>
</Entry>
<Entry>
<Term>t</Term>
<Count>1</Count>
</Entry>
<Entry>
<Term>the</Term>
<Count>1</Count>
</Entry>
<Entry>
<Term>to</Term>
<Count>1</Count>
</Entry>
<Entry>
<Term>which</Term>
<Count>1</Count>
</Entry>
</Index>
