<?xml version="1.0" encoding="UTF-8" standalone="no"?><Index><Entry><Term>11</Term><Count>1</Count></Entry><Entry><Term>13</Term><Count>1</Count></Entry><Entry><Term>1973</Term><Count>1</Count></Entry><Entry><Term>1978</Term><Count>1</Count></Entry><Entry><Term>20</Term><Count>1</Count></Entry><Entry><Term>2431</Term><Count>6</Count></Entry><Entry><Term>5</Term><Count>3</Count></Entry><Entry><Term>513</Term><Count>1</Count></Entry><Entry><Term>541</Term><Count>1</Count></Entry><Entry><Term>A458</Term><Count>1</Count></Entry><Entry><Term>AM</Term><Count>1</Count></Entry><Entry><Term>Algorithm</Term><Count>1</Count></Entry><Entry><Term>Approximation</Term><Count>1</Count></Entry><Entry><Term>CA731009</Term><Count>1</Count></Entry><Entry><Term>CACM</Term><Count>1</Count></Entry><Entry><Term>D</Term><Count>1</Count></Entry><Entry><Term>Discrete</Term><Count>1</Count></Entry><Entry><Term>E2</Term><Count>1</Count></Entry><Entry><Term>JB</Term><Count>1</Count></Entry><Entry><Term>January</Term><Count>1</Count></Entry><Entry><Term>L1</Term><Count>2</Count></Entry><Entry><Term>Linear</Term><Count>2</Count></Entry><Entry><Term>October</Term><Count>1</Count></Entry><Entry><Term>P</Term><Count>1</Count></Entry><Entry><Term>Programming</Term><Count>1</Count></Entry><Entry><Term>Robers</Term><Count>2</Count></Entry><Entry><Term>S</Term><Count>2</Count></Entry><Entry><Term>approximation</Term><Count>2</Count></Entry><Entry><Term>by</Term><Count>1</Count></Entry><Entry><Term>discrete</Term><Count>1</Count></Entry><Entry><Term>interval</Term><Count>1</Count></Entry></Index>