<?xml version="1.0" encoding="UTF-8" standalone="no"?>
<Index>
<Entry>
<Term>10</Term>
<Count>1</Count>
</Entry>
<Entry>
<Term>12</Term>
<Count>1</Count>
</Entry>
<Entry>
<Term>1975</Term>
<Count>1</Count>
</Entry>
<Entry>
<Term>1978</Term>
<Count>1</Count>
</Entry>
<Entry>
<Term>2805</Term>
<Count>6</Count>
</Entry>
<Entry>
<Term>31</Term>
<Count>1</Count>
</Entry>
<Entry>
<Term>5</Term>
<Count>3</Count>
</Entry>
<Entry>
<Term>514</Term>
<Count>1</Count>
</Entry>
<Entry>
<Term>A</Term>
<Count>1</Count>
</Entry>
<Entry>
<Term>AM</Term>
<Count>1</Count>
</Entry>
<Entry>
<Term>CA750106</Term>
<Count>1</Count>
</Entry>
<Entry>
<Term>CACM</Term>
<Count>1</Count>
</Entry>
<Entry>
<Term>Eigenvalues</Term>
<Count>1</Count>
</Entry>
<Entry>
<Term>Frobenius</Term>
<Count>1</Count>
</Entry>
<Entry>
<Term>Gershgorin</Term>
<Count>1</Count>
</Entry>
<Entry>
<Term>JB</Term>
<Count>1</Count>
</Entry>
<Entry>
<Term>January</Term>
<Count>2</Count>
</Entry>
<Entry>
<Term>Matrices</Term>
<Count>1</Count>
</Entry>
<Entry>
<Term>Non</Term>
<Count>1</Count>
</Entry>
<Entry>
<Term>Perturbations</Term>
<Count>1</Count>
</Entry>
<Entry>
<Term>Sluis</Term>
<Count>1</Count>
</Entry>
<Entry>
<Term>The</Term>
<Count>2</Count>
</Entry>
<Entry>
<Term>almost</Term>
<Count>1</Count>
</Entry>
<Entry>
<Term>and</Term>
<Count>2</Count>
</Entry>
<Entry>
<Term>any</Term>
<Count>1</Count>
</Entry>
<Entry>
<Term>are</Term>
<Count>3</Count>
</Entry>
<Entry>
<Term>attainable</Term>
<Count>1</Count>
</Entry>
<Entry>
<Term>be</Term>
<Count>1</Count>
</Entry>
<Entry>
<Term>bounds</Term>
<Count>3</Count>
</Entry>
<Entry>
<Term>but</Term>
<Count>1</Count>
</Entry>
<Entry>
<Term>circles</Term>
<Count>1</Count>
</Entry>
<Entry>
<Term>considered</Term>
<Count>1</Count>
</Entry>
<Entry>
<Term>departure</Term>
<Count>2</Count>
</Entry>
<Entry>
<Term>der</Term>
<Count>1</Count>
</Entry>
<Entry>
<Term>derived</Term>
<Count>1</Count>
</Entry>
<Entry>
<Term>eigen</Term>
<Count>1</Count>
</Entry>
<Entry>
<Term>eigenvalues</Term>
<Count>3</Count>
</Entry>
<Entry>
<Term>finite</Term>
<Count>1</Count>
</Entry>
<Entry>
<Term>for</Term>
<Count>2</Count>
</Entry>
<Entry>
<Term>from</Term>
<Count>2</Count>
</Entry>
<Entry>
<Term>give</Term>
<Count>1</Count>
</Entry>
<Entry>
<Term>in</Term>
<Count>2</Count>
</Entry>
<Entry>
<Term>is</Term>
<Count>1</Count>
</Entry>
<Entry>
<Term>matrices</Term>
<Count>3</Count>
</Entry>
<Entry>
<Term>matrix</Term>
<Count>1</Count>
</Entry>
<Entry>
<Term>multiple</Term>
<Count>1</Count>
</Entry>
<Entry>
<Term>non</Term>
<Count>1</Count>
</Entry>
<Entry>
<Term>nonnormal</Term>
<Count>1</Count>
</Entry>
<Entry>
<Term>norm</Term>
<Count>1</Count>
</Entry>
<Entry>
<Term>normal</Term>
<Count>2</Count>
</Entry>
<Entry>
<Term>normality</Term>
<Count>2</Count>
</Entry>
<Entry>
<Term>not</Term>
<Count>1</Count>
</Entry>
<Entry>
<Term>of</Term>
<Count>9</Count>
</Entry>
<Entry>
<Term>perturbation</Term>
<Count>2</Count>
</Entry>
<Entry>
<Term>perturbations</Term>
<Count>1</Count>
</Entry>
<Entry>
<Term>problem</Term>
<Count>1</Count>
</Entry>
<Entry>
<Term>set</Term>
<Count>1</Count>
</Entry>
<Entry>
<Term>shown</Term>
<Count>1</Count>
</Entry>
<Entry>
<Term>simple</Term>
<Count>1</Count>
</Entry>
<Entry>
<Term>system</Term>
<Count>1</Count>
</Entry>
<Entry>
<Term>terms</Term>
<Count>2</Count>
</Entry>
<Entry>
<Term>the</Term>
<Count>5</Count>
</Entry>
<Entry>
<Term>these</Term>
<Count>1</Count>
</Entry>
<Entry>
<Term>to</Term>
<Count>2</Count>
</Entry>
<Entry>
<Term>van</Term>
<Count>1</Count>
</Entry>
<Entry>
<Term>where</Term>
<Count>1</Count>
</Entry>
<Entry>
<Term>which</Term>
<Count>1</Count>
</Entry>
</Index>
