<?xml version="1.0" encoding="UTF-8" standalone="no"?><Index><Entry><Term>13</Term><Count>1</Count></Entry><Entry><Term>17</Term><Count>1</Count></Entry><Entry><Term>1979</Term><Count>1</Count></Entry><Entry><Term>1980</Term><Count>1</Count></Entry><Entry><Term>20</Term><Count>1</Count></Entry><Entry><Term>3171</Term><Count>6</Count></Entry><Entry><Term>4</Term><Count>2</Count></Entry><Entry><Term>412</Term><Count>1</Count></Entry><Entry><Term>442</Term><Count>1</Count></Entry><Entry><Term>5</Term><Count>3</Count></Entry><Entry><Term>57</Term><Count>1</Count></Entry><Entry><Term>9</Term><Count>1</Count></Entry><Entry><Term>A</Term><Count>1</Count></Entry><Entry><Term>AM</Term><Count>1</Count></Entry><Entry><Term>CA791004</Term><Count>1</Count></Entry><Entry><Term>CACM</Term><Count>1</Count></Entry><Entry><Term>Cheap</Term><Count>1</Count></Entry><Entry><Term>DB</Term><Count>1</Count></Entry><Entry><Term>January</Term><Count>1</Count></Entry><Entry><Term>Klint</Term><Count>1</Count></Entry><Entry><Term>Line</Term><Count>2</Count></Entry><Entry><Term>Made</Term><Count>1</Count></Entry><Entry><Term>Numbers</Term><Count>1</Count></Entry><Entry><Term>October</Term><Count>1</Count></Entry><Entry><Term>P</Term><Count>1</Count></Entry><Entry><Term>Under</Term><Count>1</Count></Entry><Entry><Term>absolutely</Term><Count>1</Count></Entry><Entry><Term>abstract</Term><Count>1</Count></Entry><Entry><Term>administration</Term><Count>2</Count></Entry><Entry><Term>be</Term><Count>1</Count></Entry><Entry><Term>circumstances</Term><Count>1</Count></Entry><Entry><Term>code</Term><Count>1</Count></Entry><Entry><Term>described</Term><Count>1</Count></Entry><Entry><Term>diagnostic</Term><Count>1</Count></Entry><Entry><Term>during</Term><Count>1</Count></Entry><Entry><Term>either</Term><Count>1</Count></Entry><Entry><Term>execution</Term><Count>1</Count></Entry><Entry><Term>for</Term><Count>2</Count></Entry><Entry><Term>high</Term><Count>1</Count></Entry><Entry><Term>implementations</Term><Count>1</Count></Entry><Entry><Term>in</Term><Count>1</Count></Entry><Entry><Term>is</Term><Count>1</Count></Entry><Entry><Term>languages</Term><Count>1</Count></Entry><Entry><Term>level</Term><Count>1</Count></Entry><Entry><Term>line</Term><Count>1</Count></Entry><Entry><Term>machine</Term><Count>1</Count></Entry><Entry><Term>messages</Term><Count>1</Count></Entry><Entry><Term>method</Term><Count>1</Count></Entry><Entry><Term>no</Term><Count>1</Count></Entry><Entry><Term>number</Term><Count>2</Count></Entry><Entry><Term>of</Term><Count>2</Count></Entry><Entry><Term>or</Term><Count>1</Count></Entry><Entry><Term>overhead</Term><Count>1</Count></Entry><Entry><Term>program</Term><Count>1</Count></Entry><Entry><Term>requires</Term><Count>1</Count></Entry><Entry><Term>run</Term><Count>1</Count></Entry><Entry><Term>space</Term><Count>1</Count></Entry><Entry><Term>suitable</Term><Count>1</Count></Entry><Entry><Term>technique</Term><Count>1</Count></Entry><Entry><Term>the</Term><Count>1</Count></Entry><Entry><Term>this</Term><Count>1</Count></Entry><Entry><Term>time</Term><Count>2</Count></Entry><Entry><Term>to</Term><Count>1</Count></Entry><Entry><Term>used</Term><Count>1</Count></Entry></Index>