<?xml version="1.0" encoding="UTF-8" standalone="no"?>
<Index>
<Entry>
<Term>1231</Term>
<Count>1</Count>
</Entry>
<Entry>
<Term>1565</Term>
<Count>1</Count>
</Entry>
<Entry>
<Term>1852</Term>
<Count>1</Count>
</Entry>
<Entry>
<Term>1926</Term>
<Count>14</Count>
</Entry>
<Entry>
<Term>1947</Term>
<Count>1</Count>
</Entry>
<Entry>
<Term>1969</Term>
<Count>1</Count>
</Entry>
<Entry>
<Term>1978</Term>
<Count>1</Count>
</Entry>
<Entry>
<Term>20</Term>
<Count>1</Count>
</Entry>
<Entry>
<Term>2034</Term>
<Count>1</Count>
</Entry>
<Entry>
<Term>3</Term>
<Count>1</Count>
</Entry>
<Entry>
<Term>374</Term>
<Count>1</Count>
</Entry>
<Entry>
<Term>39</Term>
<Count>1</Count>
</Entry>
<Entry>
<Term>45</Term>
<Count>1</Count>
</Entry>
<Entry>
<Term>5</Term>
<Count>4</Count>
</Entry>
<Entry>
<Term>6</Term>
<Count>6</Count>
</Entry>
<Entry>
<Term>64k</Term>
<Count>1</Count>
</Entry>
<Entry>
<Term>75</Term>
<Count>1</Count>
</Entry>
<Entry>
<Term>9</Term>
<Count>1</Count>
</Entry>
<Entry>
<Term>984</Term>
<Count>1</Count>
</Entry>
<Entry>
<Term>AM</Term>
<Count>1</Count>
</Entry>
<Entry>
<Term>Berns</Term>
<Count>1</Count>
</Entry>
<Entry>
<Term>CA690301</Term>
<Count>1</Count>
</Entry>
<Entry>
<Term>CACM</Term>
<Count>1</Count>
</Entry>
<Entry>
<Term>Description</Term>
<Count>1</Count>
</Entry>
<Entry>
<Term>FORMAT</Term>
<Count>2</Count>
</Entry>
<Entry>
<Term>FORTRAN</Term>
<Count>1</Count>
</Entry>
<Entry>
<Term>February</Term>
<Count>1</Count>
</Entry>
<Entry>
<Term>G</Term>
<Count>1</Count>
</Entry>
<Entry>
<Term>IV</Term>
<Count>1</Count>
</Entry>
<Entry>
<Term>It</Term>
<Count>2</Count>
</Entry>
<Entry>
<Term>JB</Term>
<Count>1</Count>
</Entry>
<Entry>
<Term>M</Term>
<Count>1</Count>
</Entry>
<Entry>
<Term>March</Term>
<Count>1</Count>
</Entry>
<Entry>
<Term>Processing</Term>
<Count>1</Count>
</Entry>
<Entry>
<Term>Program</Term>
<Count>1</Count>
</Entry>
<Entry>
<Term>Text</Term>
<Count>1</Count>
</Entry>
<Entry>
<Term>a</Term>
<Count>4</Count>
</Entry>
<Entry>
<Term>aids</Term>
<Count>1</Count>
</Entry>
<Entry>
<Term>and</Term>
<Count>2</Count>
</Entry>
<Entry>
<Term>automatic</Term>
<Count>1</Count>
</Entry>
<Entry>
<Term>capabilities</Term>
<Count>1</Count>
</Entry>
<Entry>
<Term>capitalization</Term>
<Count>1</Count>
</Entry>
<Entry>
<Term>columns</Term>
<Count>1</Count>
</Entry>
<Entry>
<Term>computer</Term>
<Count>1</Count>
</Entry>
<Entry>
<Term>construction</Term>
<Count>1</Count>
</Entry>
<Entry>
<Term>dictionary</Term>
<Count>1</Count>
</Entry>
<Entry>
<Term>directly</Term>
<Count>1</Count>
</Entry>
<Entry>
<Term>documentation</Term>
<Count>1</Count>
</Entry>
<Entry>
<Term>documents</Term>
<Count>1</Count>
</Entry>
<Entry>
<Term>editing</Term>
<Count>2</Count>
</Entry>
<Entry>
<Term>eight</Term>
<Count>1</Count>
</Entry>
<Entry>
<Term>entirely</Term>
<Count>1</Count>
</Entry>
<Entry>
<Term>facilitates</Term>
<Count>1</Count>
</Entry>
<Entry>
<Term>features</Term>
<Count>1</Count>
</Entry>
<Entry>
<Term>finished</Term>
<Count>1</Count>
</Entry>
<Entry>
<Term>flexible</Term>
<Count>1</Count>
</Entry>
<Entry>
<Term>for</Term>
<Count>1</Count>
</Entry>
<Entry>
<Term>form</Term>
<Count>1</Count>
</Entry>
<Entry>
<Term>formatting</Term>
<Count>2</Count>
</Entry>
<Entry>
<Term>free</Term>
<Count>1</Count>
</Entry>
<Entry>
<Term>frequency</Term>
<Count>1</Count>
</Entry>
<Entry>
<Term>good</Term>
<Count>1</Count>
</Entry>
<Entry>
<Term>in</Term>
<Count>1</Count>
</Entry>
<Entry>
<Term>including</Term>
<Count>1</Count>
</Entry>
<Entry>
<Term>index</Term>
<Count>1</Count>
</Entry>
<Entry>
<Term>indexing</Term>
<Count>1</Count>
</Entry>
<Entry>
<Term>input</Term>
<Count>1</Count>
</Entry>
<Entry>
<Term>is</Term>
<Count>2</Count>
</Entry>
<Entry>
<Term>items</Term>
<Count>1</Count>
</Entry>
<Entry>
<Term>justification</Term>
<Count>1</Count>
</Entry>
<Entry>
<Term>minimum</Term>
<Count>1</Count>
</Entry>
<Entry>
<Term>nontext</Term>
<Count>1</Count>
</Entry>
<Entry>
<Term>of</Term>
<Count>4</Count>
</Entry>
<Entry>
<Term>on</Term>
<Count>1</Count>
</Entry>
<Entry>
<Term>page</Term>
<Count>1</Count>
</Entry>
<Entry>
<Term>per</Term>
<Count>1</Count>
</Entry>
<Entry>
<Term>performance</Term>
<Count>1</Count>
</Entry>
<Entry>
<Term>printer</Term>
<Count>1</Count>
</Entry>
<Entry>
<Term>printing</Term>
<Count>2</Count>
</Entry>
<Entry>
<Term>processing</Term>
<Count>1</Count>
</Entry>
<Entry>
<Term>production</Term>
<Count>1</Count>
</Entry>
<Entry>
<Term>program</Term>
<Count>1</Count>
</Entry>
<Entry>
<Term>relatively</Term>
<Count>1</Count>
</Entry>
<Entry>
<Term>right</Term>
<Count>1</Count>
</Entry>
<Entry>
<Term>small</Term>
<Count>1</Count>
</Entry>
<Entry>
<Term>system</Term>
<Count>1</Count>
</Entry>
<Entry>
<Term>text</Term>
<Count>2</Count>
</Entry>
<Entry>
<Term>the</Term>
<Count>2</Count>
</Entry>
<Entry>
<Term>to</Term>
<Count>1</Count>
</Entry>
<Entry>
<Term>totally</Term>
<Count>1</Count>
</Entry>
<Entry>
<Term>up</Term>
<Count>1</Count>
</Entry>
<Entry>
<Term>very</Term>
<Count>1</Count>
</Entry>
<Entry>
<Term>vocabulary</Term>
<Count>1</Count>
</Entry>
<Entry>
<Term>which</Term>
<Count>1</Count>
</Entry>
<Entry>
<Term>written</Term>
<Count>1</Count>
</Entry>
</Index>
