<?xml version="1.0" encoding="UTF-8" standalone="no"?><Index><Entry><Term>1964</Term><Count>1</Count></Entry><Entry><Term>1978</Term><Count>1</Count></Entry><Entry><Term>27</Term><Count>1</Count></Entry><Entry><Term>3</Term><Count>1</Count></Entry><Entry><Term>5</Term><Count>3</Count></Entry><Entry><Term>9</Term><Count>1</Count></Entry><Entry><Term>961</Term><Count>6</Count></Entry><Entry><Term>A</Term><Count>1</Count></Entry><Entry><Term>BCD</Term><Count>1</Count></Entry><Entry><Term>Binary</Term><Count>1</Count></Entry><Entry><Term>Bit</Term><Count>1</Count></Entry><Entry><Term>C</Term><Count>1</Count></Entry><Entry><Term>CA641210</Term><Count>1</Count></Entry><Entry><Term>CACM</Term><Count>1</Count></Entry><Entry><Term>December</Term><Count>1</Count></Entry><Entry><Term>FORTRAN</Term><Count>2</Count></Entry><Entry><Term>II</Term><Count>2</Count></Entry><Entry><Term>JB</Term><Count>1</Count></Entry><Entry><Term>Limited</Term><Count>1</Count></Entry><Entry><Term>Manipulation</Term><Count>1</Count></Entry><Entry><Term>March</Term><Count>1</Count></Entry><Entry><Term>Oster</Term><Count>1</Count></Entry><Entry><Term>PM</Term><Count>1</Count></Entry><Entry><Term>Techniques</Term><Count>1</Count></Entry><Entry><Term>These</Term><Count>1</Count></Entry><Entry><Term>Using</Term><Count>1</Count></Entry><Entry><Term>allow</Term><Count>1</Count></Entry><Entry><Term>and</Term><Count>1</Count></Entry><Entry><Term>are</Term><Count>1</Count></Entry><Entry><Term>be</Term><Count>3</Count></Entry><Entry><Term>bits</Term><Count>2</Count></Entry><Entry><Term>certain</Term><Count>1</Count></Entry><Entry><Term>coded</Term><Count>1</Count></Entry><Entry><Term>converted</Term><Count>1</Count></Entry><Entry><Term>developed</Term><Count>1</Count></Entry><Entry><Term>fields</Term><Count>1</Count></Entry><Entry><Term>for</Term><Count>1</Count></Entry><Entry><Term>in</Term><Count>1</Count></Entry><Entry><Term>individual</Term><Count>1</Count></Entry><Entry><Term>manipulating</Term><Count>1</Count></Entry><Entry><Term>numbers</Term><Count>1</Count></Entry><Entry><Term>only</Term><Count>1</Count></Entry><Entry><Term>shifted</Term><Count>1</Count></Entry><Entry><Term>techniques</Term><Count>1</Count></Entry><Entry><Term>tested</Term><Count>1</Count></Entry><Entry><Term>to</Term><Count>4</Count></Entry><Entry><Term>using</Term><Count>1</Count></Entry></Index>